<?xml version="1.0" encoding="UTF-8"?>
<jcr:root xmlns:sling="http://sling.apache.org/jcr/sling/1.0" xmlns:jcr="http://www.jcp.org/jcr/1.0" xmlns:nt="http://www.jcp.org/jcr/nt/1.0"
    jcr:primaryType="sling:OrderedFolder">
    <jcr:content
        jcr:primaryType="nt:unstructured"
        jcr:title="aemApp">
        <folderThumbnail/>
    </jcr:content>
    <asset.jpg/>
    <Beanz_Icon_Find_Your_Match.webp/>
    <Beanz_Icon_Keep_It_Fresh.webp/>
    <Beanz_Website_3000x1536_Homepage_Header_B_new_x0020__x0028_1_x0029_.webp/>
    <Beanz_Website_3000x1536_Homepage_Header_B_new.webp/>
    <beanz-white.svg/>
    <BeanzUS_YesPlz_logo_200x200.jpg/>
    <klatch-banner.jpeg/>
    <filter-coffee.png/>
    <espresso-coffee.png/>
    <coffee-101.webp/>
    <beanz-by-breville-logo-white.svg/>
    <Beanz_Icon_Subscribe_and_Save.webp/>
    <Beanz_Icon_Homegrown_Roasters.webp/>
</jcr:root>
